retail_scraper/__init__.py
retail_scraper/spiders/__init__.py
retail_scraper/spiders/sephora.py
retail_scraper/spiders/ulta.py
retail_scraper/spiders/utils.py
retail_scraper-1.1.dist-info/LICENSE
retail_scraper-1.1.dist-info/METADATA
retail_scraper-1.1.dist-info/WHEEL
retail_scraper-1.1.dist-info/top_level.txt
retail_scraper-1.1.dist-info/RECORD
