Metadata-Version: 2.1
Name: retail-scraper
Version: 1.1
Summary: Ecommerce scrapers library
Home-page: https://github.com/hamidnahli/rs-app
Author: Hamid Nahli
Author-email: hamidnahlirss@gmail.com
License: UNKNOWN
Platform: UNKNOWN
Classifier: Programming Language :: Python :: 3
Classifier: License :: OSI Approved :: MIT License
Classifier: Operating System :: OS Independent
Requires-Python: >=3.8
License-File: LICENSE
